sfzh/__init__.py
sfzh-0.0.1.dist-info/METADATA
sfzh-0.0.1.dist-info/WHEEL
sfzh-0.0.1.dist-info/top_level.txt
sfzh-0.0.1.dist-info/RECORD
